{"time":{"updated":"May 31, 2021 19:31:00 UTC","updatedISO":"2021-05-31T19:31:00+00:00","updateduk":"May 31, 2021 at 20:31 BST"},"disclaimer":"This data was produced from the CoinDesk Bitcoin Price Index (USD). Non-USD currency data converted using hourly conversion rate from openexchangerates.org","chartName":"Bitcoin","bpi":{"USD":{"code":"USD","symbol":"&#36;","rate":"36,722.8417","description":"United States Dollar","rate_float":36722.8417},"GBP":{"code":"GBP","symbol":"&pound;","rate":"25,853.2110","description":"British Pound Sterling","rate_float":25853.211},"EUR":{"code":"EUR","symbol":"&euro;","rate":"30,032.1235","description":"Euro","rate_float":30032.1235},"CNY":{"code":"CNY","symbol":"&yen;","rate":"40,202.5000","description":"Chinese Yuan","rate_float":40202.5}}}